CHANGELOG.txt
LICENSE.txt
MANIFEST.in
README.txt
setup.py
testing.py
textimage/__init__.py
textimage.egg-info/PKG-INFO
textimage.egg-info/SOURCES.txt
textimage.egg-info/dependency_links.txt
textimage.egg-info/requires.txt
textimage.egg-info/top_level.txt