Metadata-Version: 1.0
Name: textimage
Version: 1.0.2
Summary: puts text on image
Home-page: UNKNOWN
Author: HYKANTUS
Author-email: hykantus@gmail.com
License: UNKNOWN
Keywords: Pillow,PIL,Image Manipulation,text,text on image
Platform: UNKNOWN
